medcalc/__init__.py
medcalc/__main__.py
medcalc/calculator.py
medcalc-0.3.0.dist-info/METADATA
medcalc-0.3.0.dist-info/WHEEL
medcalc-0.3.0.dist-info/entry_points.txt
medcalc-0.3.0.dist-info/top_level.txt
medcalc-0.3.0.dist-info/RECORD
