Metadata-Version: 2.4
Name: medcalc
Version: 0.3.0
Summary: MCP server for Medical Calculation
Author-email: Sungji Wang <sungjiwang@snu.ac.kr>, Hyung-Chul Lee <vital@snu.ac.kr>
License-Expression: MIT
Requires-Python: >=3.12
Requires-Dist: scipy
Requires-Dist: mcp
